GitMinglingDaquan/README.md
GitMinglingDaquan/__init__.py
GitMinglingDaquan/__main__.py
GitMinglingDaquan/file.epub
GitMinglingDaquan/index.html
GitMinglingDaquan/css/__init__.py
GitMinglingDaquan/css/annotations.css
GitMinglingDaquan/css/main.css
GitMinglingDaquan/css/normalize.css
GitMinglingDaquan/css/popup.css
GitMinglingDaquan/font/__init__.py
GitMinglingDaquan/font/fontello.eot
GitMinglingDaquan/font/fontello.svg
GitMinglingDaquan/font/fontello.ttf
GitMinglingDaquan/font/fontello.woff
GitMinglingDaquan/img/__init__.py
GitMinglingDaquan/img/annotator-glyph-sprite.png
GitMinglingDaquan/img/annotator-icon-sprite.png
GitMinglingDaquan/img/apple-touch-icon.png
GitMinglingDaquan/img/cancelfullscreen.png
GitMinglingDaquan/img/close.png
GitMinglingDaquan/img/fullscreen.png
GitMinglingDaquan/img/loader.gif
GitMinglingDaquan/img/menu-icon.png
GitMinglingDaquan/img/save.png
GitMinglingDaquan/img/saved.png
GitMinglingDaquan/img/settings-s.png
GitMinglingDaquan/img/settings.png
GitMinglingDaquan/img/star.png
GitMinglingDaquan/js/__init__.py
GitMinglingDaquan/js/epub.js
GitMinglingDaquan/js/epub.min.js
GitMinglingDaquan/js/epub.min.map
GitMinglingDaquan/js/hooks.min.js
GitMinglingDaquan/js/hooks.min.map
GitMinglingDaquan/js/reader.js
GitMinglingDaquan/js/reader.js.map
GitMinglingDaquan/js/reader.min.js
GitMinglingDaquan/js/reader.min.map
GitMinglingDaquan/js/hooks/__init__.py
GitMinglingDaquan/js/hooks/extensions/__init__.py
GitMinglingDaquan/js/hooks/extensions/highlight.js
GitMinglingDaquan/js/libs/__init__.py
GitMinglingDaquan/js/libs/jquery.min.js
GitMinglingDaquan/js/libs/localforage.min.js
GitMinglingDaquan/js/libs/screenfull.js
GitMinglingDaquan/js/libs/screenfull.min.js
GitMinglingDaquan/js/libs/zip.min.js
GitMinglingDaquan/js/plugins/__init__.py
GitMinglingDaquan/js/plugins/hypothesis.js
GitMinglingDaquan/js/plugins/search.js
git_mingling_daquan-2024.3.5.0.dist-info/METADATA
git_mingling_daquan-2024.3.5.0.dist-info/WHEEL
git_mingling_daquan-2024.3.5.0.dist-info/entry_points.txt
git_mingling_daquan-2024.3.5.0.dist-info/top_level.txt
git_mingling_daquan-2024.3.5.0.dist-info/RECORD
